netbox_better_templates/__init__.py
netbox_better_templates/_version.py
netbox_better_templates/monkey_patches/__init__.py
netbox_better_templates/monkey_patches/_config_template.py
netbox_better_templates-1.0.2.dist-info/licenses/LICENSE
netbox_better_templates-1.0.2.dist-info/METADATA
netbox_better_templates-1.0.2.dist-info/WHEEL
netbox_better_templates-1.0.2.dist-info/top_level.txt
netbox_better_templates-1.0.2.dist-info/RECORD
