Metadata-Version: 2.4
Name: netbox_better_templates
Version: 1.0.2
Summary: Adds some functionality to netbox templates and config render.
Home-page: https://github.com/radin-system/netbox-better-templates
Author: Radin System
Author-email: Radin-System <technical@rsto.ir>
Project-URL: Homepage, https://github.com/Radin-System/netbox-better-templates
Project-URL: BugTracker, https://github.com/Radin-System/netbox-better-templates/issues
Keywords: python,netbox,provisioning,template,jinja,jinja2
Classifier: Programming Language :: Python :: 3
Classifier: License :: OSI Approved :: MIT License
Classifier: Operating System :: OS Independent
Requires-Python: >=3.11
License-File: LICENSE
Dynamic: author
Dynamic: home-page
Dynamic: license-file
